RobotFrameworkRequests/__init__.py
RobotFrameworkRequests/lib/__init__.py
RobotFrameworkRequests/main/__init__.py
RobotFrameworkRequests/main/action.py
RobotFrameworkRequests/main/common.py
movoid_robotframework_requests-1.0.6.dist-info/METADATA
movoid_robotframework_requests-1.0.6.dist-info/WHEEL
movoid_robotframework_requests-1.0.6.dist-info/top_level.txt
movoid_robotframework_requests-1.0.6.dist-info/RECORD
