Metadata-Version: 2.1
Name: movoid_robotframework_requests
Version: 1.0.6
Home-page: 
Author: movoid
Author-email: bobrobotsun@163.com
Requires-Dist: requests
Requires-Dist: psutil
Requires-Dist: movoid-function >=1.7.1
Requires-Dist: movoid-package
Requires-Dist: movoid-robotframework
Requires-Dist: robotframework-requests
